{
  "id": "02-22_the_chair_of_saint_peter_the_apostle",
  "name": "The Chair of Saint Peter the Apostle",
  "mmdd": "02-22",
  "feast": "The Twenty-Second Day of February",
  "summary": "The Chair of Saint Peter, also known as the Throne of Saint Peter, is a relic conserved in St. Peter's Basilica in Vatican City, the sovereign enclave of the Pope inside Rome, Italy. The relic is a wooden throne that tradition claims belonged to the Apostle Saint Peter, the leader of the Early Christians in Rome and first Pope, and which he used as Bishop of Rome. The relic is enclosed in a sculpted gilt bronze casing designed by Gian Lorenzo Bernini and constructed between 1647 and 1653. In 2012, Pope Benedict XVI described the chair as \"a symbol of the special mission of Peter and his Successors to tend Christ's flock, keeping it united in faith and in charity.\"",
  "biography": "The Chair of Saint Peter (Latin: Cathedra Petri), also known as the Throne of Saint Peter, is a relic conserved in St. Peter's Basilica in Vatican City, the sovereign enclave of the Pope inside Rome, Italy. The relic is a wooden throne that tradition claims belonged to the Apostle Saint Peter, the leader of the Early Christians in Rome and first Pope, and which he used as Bishop of Rome. The relic is enclosed in a sculpted gilt bronze casing designed by Gian Lorenzo Bernini and constructed between 1647 and 1653. In 2012, Pope Benedict XVI described the chair as \"a symbol of the special mission of Peter and his Successors to tend Christ's flock, keeping it united in faith and in charity.\" The wooden throne was a gift from Emperor of the Romans Charles the Bald to Pope John VIII in 875. It has been studied many times over the years, most recently between 1968 and 1974. The study concluded that it was not a double, but a single chair, with a covering, and that the oldest parts are from the 6th century. The Chair of Saint Peter is the second altar within the church, with the first one being the one under St. Peter's Baldachin.",
  "prayers": [],
  "sources": [
    "https://en.wikipedia.org/wiki/Chair_of_Saint_Peter",
    "Wikipedia (CC BY-SA) — text attribution required."
  ],
  "photoUrl": "https://sanctuaryapp-media-prod.s3.us-east-1.amazonaws.com/saints/02-22_the_chair_of_saint_peter_the_apostle.jpg",
  "_translationMeta": {
    "version": 1,
    "fields": {
      "name": {
        "sourceHash": "650c0511606c680a94ebe7f435c5525f3f500e91e0dc3da511d29c0a18abb8be",
        "langs": {
          "es": {
            "translatedHash": "0eb0afe776aa903b9665345398de21e859cac4da2aa25ef90317bdbdf15117fe",
            "updatedAt": "2026-02-24T22:40:42.342Z"
          },
          "pl": {
            "translatedHash": "2fc72a1eff61f9e26d18e0c3233543957f82b6f12041138d4c8376d1c98e9036",
            "updatedAt": "2026-02-24T22:40:42.972Z"
          }
        }
      },
      "feast": {
        "sourceHash": "e71335a07289b1a667cad95ac4c766c24d1afb3669dfa3e9c3ab887c910825a1",
        "langs": {
          "es": {
            "translatedHash": "873884a7dfa59773408641a743c5301cc9fdbc2d1ad7a2869900cd40559bec41",
            "updatedAt": "2026-02-24T22:40:43.653Z"
          },
          "pl": {
            "translatedHash": "4f45f6f742d44917b8276e31e812bc2193e9c96d5b3510ede60decbf60033007",
            "updatedAt": "2026-02-24T22:40:44.274Z"
          }
        }
      },
      "summary": {
        "sourceHash": "8ffc8a344cd56725f0a8ca18f7da82e4ec6a9851d9391958277a66095c397299",
        "langs": {
          "es": {
            "translatedHash": "ce51c56dc89f764d52ec0cfc7e4564137ddb6fca73b31938a970962760307366",
            "updatedAt": "2026-02-24T22:40:47.170Z"
          },
          "pl": {
            "translatedHash": "843dc84cd29ccef8187e465e66a44ef268b3039d09c7c14fae709845153fd778",
            "updatedAt": "2026-02-24T22:40:51.617Z"
          }
        }
      },
      "biography": {
        "sourceHash": "a895b745bf21dcbca06be67b5e989325e15239380b59d6f46c0677fec3528a84",
        "langs": {
          "es": {
            "translatedHash": "4fcb7b169e3c2201c9a3fe31c2dfc2bdb3695db1a2e5c15b67ad74ac3d8b12e5",
            "updatedAt": "2026-02-24T22:40:56.902Z"
          },
          "pl": {
            "translatedHash": "173100d8ca3e8d91a7fb4b15720311c70016a80b291c944baffe695d8be6701a",
            "updatedAt": "2026-02-24T22:41:04.407Z"
          }
        }
      }
    }
  },
  "name_es": "La Silla de San Pedro Apóstol",
  "name_pl": "Tron Świętego Piotra Apostoła",
  "feast_es": "El Vigésimo Segundo Día de Febrero",
  "feast_pl": "Dwudziesty drugi dzień lutego",
  "summary_es": "La Silla de San Pedro, también conocida como el Trono de San Pedro, es una reliquia conservada en la Basílica de San Pedro en la Ciudad del Vaticano, el enclave soberano del Papa dentro de Roma, Italia. La reliquia es un trono de madera que la tradición atribuye al Apóstol San Pedro, el líder de los primeros cristianos en Roma y primer Papa, y que él usó como Obispo de Roma. La reliquia está encerrada en una caja de bronce dorado esculpida, diseñada por Gian Lorenzo Bernini y construida entre 1647 y 1653. En 2012, el Papa Benedicto XVI describió la silla como \"un símbolo de la misión especial de Pedro y sus Sucesores para cuidar el rebaño de Cristo, manteniéndolo unido en la fe y en la caridad.\"",
  "summary_pl": "Tron Świętego Piotra, znany również jako Fotel Świętego Piotra, jest relikwią przechowywaną w Bazylice św. Piotra w Watykanie, suwerennej enklawie papieża w Rzymie, we Włoszech. Relikwia to drewniany tron, który według tradycji należał do Apostoła Świętego Piotra, przywódcy wczesnych chrześcijan w Rzymie i pierwszego papieża, i którego używał jako biskup Rzymu. Relikwia jest zamknięta w rzeźbionej, pozłacanej obudowie z brązu, zaprojektowanej przez Gian Lorenzo Berniniego i wykonanej w latach 1647–1653. W 2012 roku papież Benedykt XVI opisał tron jako „symbol szczególnej misji Piotra i jego Następców, by troszczyć się o owczarnię Chrystusa, utrzymując ją w jedności wiary i miłości.”",
  "biography_es": "La Silla de San Pedro (latín: Cathedra Petri), también conocida como el Trono de San Pedro, es una reliquia conservada en la Basílica de San Pedro en la Ciudad del Vaticano, el enclave soberano del Papa dentro de Roma, Italia. La reliquia es un trono de madera que la tradición afirma perteneció al Apóstol San Pedro, el líder de los primeros cristianos en Roma y primer Papa, y que él usó como Obispo de Roma. La reliquia está encerrada en una caja de bronce dorado esculpida, diseñada por Gian Lorenzo Bernini y construida entre 1647 y 1653. En 2012, el Papa Benedicto XVI describió la silla como \"un símbolo de la misión especial de Pedro y sus Sucesores para cuidar el rebaño de Cristo, manteniéndolo unido en la fe y en la caridad.\" El trono de madera fue un regalo del Emperador de los Romanos Carlos el Calvo al Papa Juan VIII en 875. Ha sido estudiado muchas veces a lo largo de los años, más recientemente entre 1968 y 1974. El estudio concluyó que no era un doble, sino una sola silla, con una cubierta, y que las partes más antiguas datan del siglo VI. La Silla de San Pedro es el segundo altar dentro de la iglesia, siendo el primero el que está bajo el Baldaquino de San Pedro.",
  "biography_pl": "Tron Świętego Piotra (łac. Cathedra Petri), znany również jako Tron Świętego Piotra, jest relikwią przechowywaną w Bazylice św. Piotra w Watykanie, suwerennej enklawie papieża w Rzymie, Włochy. Relikwia to drewniany tron, który według tradycji należał do Apostoła Świętego Piotra, przywódcy wczesnych chrześcijan w Rzymie i pierwszego papieża, i którego używał jako biskup Rzymu. Relikwia jest zamknięta w rzeźbionej, pozłacanej obudowie z brązu zaprojektowanej przez Gian Lorenzo Berniniego i wykonanej w latach 1647–1653. W 2012 roku papież Benedykt XVI opisał tron jako „symbol szczególnej misji Piotra i jego Następców, by pielęgnować owczarnię Chrystusa, utrzymując ją w jedności wiary i miłości.” Drewniany tron był darem cesarza rzymskiego Karola Łysego dla papieża Jana VIII w 875 roku. Był wielokrotnie badany na przestrzeni lat, ostatnio w latach 1968–1974. Badania wykazały, że nie jest to podwójny, lecz pojedynczy tron z pokryciem, a najstarsze jego części pochodzą z VI wieku. Tron Świętego Piotra jest drugim ołtarzem w kościele, pierwszym jest ołtarz pod baldachimem św. Piotra."
}
